MANIFEST.in
README.rst
setup.cfg
setup.py
teste.py
rainingman/teste.py
rainingman.egg-info/PKG-INFO
rainingman.egg-info/SOURCES.txt
rainingman.egg-info/dependency_links.txt
rainingman.egg-info/entry_points.txt
rainingman.egg-info/top_level.txt