Metadata-Version: 1.1
Name: rainingman
Version: 0.1.9
Summary: Raining is a collection of scripts that gather informatio about your packages
Home-page: https://github.com/PET-UnB/pet
Author: Tiago Assuncao
Author-email: tiago@sof2u.com
License: GPL3
Keywords: debian packaging development
Platform: any
Classifier: Development Status :: 5 - Production/Stable
Classifier: Intended Audience :: Developers
Classifier: Topic :: Software Development :: Build Tools
Classifier: Topic :: Software Development :: Bug Tracking
Classifier: Topic :: Software Development :: Libraries :: Perl Modules
Classifier: Topic :: Software Development :: Version Control
Classifier: License :: OSI Approved :: GNU General Public License v3 (GPLv3)
Classifier: Programming Language :: Python :: 2
Classifier: Programming Language :: Python :: 2.6
Classifier: Programming Language :: Python :: 2.7
